geots2img/__init__.py
geots2img/geots2img.py
geots2img-0.2.1.dist-info/LICENSE.txt
geots2img-0.2.1.dist-info/METADATA
geots2img-0.2.1.dist-info/WHEEL
geots2img-0.2.1.dist-info/top_level.txt
geots2img-0.2.1.dist-info/RECORD
