Metadata-Version: 2.1
Name: geots2img
Version: 0.2.1
Summary: Geo Time Series to Image
Home-page: https://github.com/juliandehoog/geo-timeseries-to-image
Author: Julian de Hoog
Author-email: julian@dehoog.ca
License: MIT
Platform: UNKNOWN
License-File: LICENSE.txt
Requires-Dist: pandas
Requires-Dist: setuptools
Requires-Dist: numpy
Requires-Dist: matplotlib
Requires-Dist: scipy
Requires-Dist: Pillow
Requires-Dist: pytz
